{"annotations":[{"start_time":9,"end_time":13,"annotation":[{"type":"paragraph","children":[{"text":"Dime cómo hacemo[s]"}]}],"tags":[{"category":"_uncategorized_","tag":"s-retention"},{"category":"Linguistic Level","tag":"phonology"},{"category":"Artists","tag":"Anitta"}],"uuid":"221108d0-e8ad-4196-bdc5-d578e7091a17"},{"start_time":13,"end_time":16,"annotation":[{"type":"paragraph","children":[{"text":"Si tú me desea[-] y yo a ti también"}]}],"tags":[{"category":"Sociolinguistic Behavior","tag":"s-reduction"},{"category":"Linguistic Level","tag":"phonology"},{"category":"Artists","tag":"Anitta"}],"uuid":"fd3f763b-b7e9-46a2-a221-830326f24f69"},{"start_time":16,"end_time":19,"annotation":[{"type":"paragraph","children":[{"text":"Hace rato te quiero comer"}]}],"tags":[{"category":"_uncategorized_","tag":"NA"}],"uuid":"c4e6ef3a-a6fa-4879-8c81-b0acee3b3938"},{"start_time":19,"end_time":21,"annotation":[{"type":"paragraph","children":[{"text":"Di que va[-] a hacer"}]}],"tags":[{"category":"Sociolinguistic Behavior","tag":"s-reduction"},{"category":"Linguistic Level","tag":"phonology"},{"category":"Artists","tag":"Anitta"}],"uuid":"56bb08a6-53d4-406e-8a88-ecdb13891643"},{"start_time":21,"end_time":24,"annotation":[{"type":"paragraph","children":[{"text":"Así que ponme un dembow que ese no re[s]peta"}]}],"tags":[{"category":"_uncategorized_","tag":"s-retention"},{"category":"Linguistic Level","tag":"phonology"},{"category":"Artists","tag":"Anitta"}],"uuid":"e3e41d84-c1de-4e72-8ca7-0f94ddebf8ca"},{"start_time":24,"end_time":27,"annotation":[{"type":"paragraph","children":[{"text":"Tengo pa' ti la combi completa que"}]}],"tags":[{"category":"_uncategorized_","tag":"NA"}],"uuid":"499cb0c4-d082-435c-b427-0c481cd9fa02"},{"start_time":27,"end_time":31,"annotation":[{"type":"paragraph","children":[{"text":"No duro mucho soltera, aprovéchame"}]}],"tags":[{"category":"_uncategorized_","tag":"NA"}],"uuid":"007e00fe-1faa-471c-9653-3dfbf18cf011"},{"start_time":31,"end_time":35,"annotation":[{"type":"paragraph","children":[{"text":"Y no te vaya[-] a envolver, sé que lo hacemo[-] y tú va[-] a volver"}]}],"tags":[{"category":"Sociolinguistic Behavior","tag":"s-reduction"},{"category":"Linguistic Level","tag":"phonology"},{"category":"Artists","tag":"Anitta"}],"uuid":"6af535bb-8f3b-4da8-b19a-805372af22a5"},{"start_time":35,"end_time":40,"annotation":[{"type":"paragraph","children":[{"text":"Un perreíto en la pared, yo soy un caso que hay que resolver"}]}],"tags":[{"category":"_uncategorized_","tag":"NA"}],"uuid":"9e665ae9-0d4e-46d0-8a80-962ab5b1f888"},{"start_time":40,"end_time":45,"annotation":[{"type":"paragraph","children":[{"text":"Pero no te vaya[-] a envolver, sé que lo hacemo[-] y tú va[-] a volver"}]}],"tags":[{"category":"Sociolinguistic Behavior","tag":"s-reduction"},{"category":"Linguistic Level","tag":"phonology"},{"category":"Artists","tag":"Anitta"}],"uuid":"8206d321-d9cf-4bc7-93d0-ac3c02d0d88c"},{"start_time":45,"end_time":49,"annotation":[{"type":"paragraph","children":[{"text":"Un perreíto pa' bellaquear"}]}],"tags":[{"category":"_uncategorized_","tag":"NA"}],"uuid":"e1c7c28c-0043-4e90-a18a-6aa49ac9d7ae"},{"start_time":49,"end_time":52,"annotation":[{"type":"paragraph","children":[{"text":"Pegaíto a la pared"}]}],"tags":[{"category":"_uncategorized_","tag":"NA"}],"uuid":"a9ecc038-558d-48f0-b1f1-217c96d3d9ad"},{"start_time":52,"end_time":54,"annotation":[{"type":"paragraph","children":[{"text":"Botelleo y fumeteo"}]}],"tags":[{"category":"_uncategorized_","tag":"NA"}],"uuid":"d678cee4-1929-4045-ad63-6d2ef20cc43d"},{"start_time":54,"end_time":57,"annotation":[{"type":"paragraph","children":[{"text":"Contigo en un capsuleo"}]}],"tags":[{"category":"_uncategorized_","tag":"NA"}],"uuid":"7f3e5139-7e4e-45c9-aad3-ed51f56be8a4"},{"start_time":57,"end_time":59,"annotation":[{"type":"paragraph","children":[{"text":"Porque siempre que te veo"}]}],"tags":[{"category":"_uncategorized_","tag":"NA"}],"uuid":"4718be03-3a0f-4ee5-a0c3-da4252387b2b"},{"start_time":59,"end_time":62,"annotation":[{"type":"paragraph","children":[{"text":"Tú me quiere[-] perrear y yo quiero partirte"}]}],"tags":[{"category":"Sociolinguistic Behavior","tag":"s-reduction"},{"category":"Linguistic Level","tag":"phonology"},{"category":"Artists","tag":"Anitta"}],"uuid":"14e5fb5a-7efc-4e16-bb97-4332bb1581bc"},{"start_time":62,"end_time":67,"annotation":[{"type":"paragraph","children":[{"text":"Cógelo a chi[-]te y en cinco minuto[-] ya va[-] a venirte"}]}],"tags":[{"category":"Sociolinguistic Behavior","tag":"s-reduction"},{"category":"Linguistic Level","tag":"phonology"},{"category":"Artists","tag":"Anitta"}],"uuid":"12525b79-680e-414b-8954-031973aec353"},{"start_time":67,"end_time":73,"annotation":[{"type":"paragraph","children":[{"text":"Me tiene[-] como pa' derretirte, sólo Dio[-] sabe lo que me hici[-]te"}]}],"tags":[{"category":"Sociolinguistic Behavior","tag":"s-reduction"},{"category":"Linguistic Level","tag":"phonology"},{"category":"Artists","tag":"Anitta"}],"uuid":"9bdd8481-9b92-4e92-85c6-a082ce232d4e"}],"set":"Default","event_id":"827af6d7-cf18-43af-a1d1-a11c6e55f36c","source_id":"dc0b0f05-3ed7-4e48-a885-e2660eb7aa66"}