{
  "audiovisual_files": {
    "dc0b0f05-3ed7-4e48-a885-e2660eb7aa66": {
      "label": "Envolver",
      "is_offline": false,
      "file_type": "Video",
      "file_url": "https://www.youtube.com/watch?v=hFCjGiawJi4",
      "duration": 0,
      "caption_set": [],
      "set_sort": []
    }
  },
  "auto_generate_web_page": true,
  "description": [
    {
      "type": "paragraph",
      "children": [
        {
          "text": ""
        }
      ]
    }
  ],
  "citation": "",
  "label": "Anitta Envolver",
  "av_file_order": [
    "dc0b0f05-3ed7-4e48-a885-e2660eb7aa66"
  ],
  "rights_statement": "https://rightsstatements.org/vocab/InC-NC/1.0/",
  "created_at": "2026-05-12T19:17:37.675Z",
  "created_by": "derrek-powell",
  "updated_at": "2026-05-12T19:17:37.675Z",
  "updated_by": "derrek-powell"
}